hdss/.DS_Store
hdss/__init__.py
hdss/src/.DS_Store
hdss/src/bezier_image.py
hdss/src/bezier_utils.py
hdss/src/create_shapes.py
hdss/src/glbl.py
hdss/src/set_params.py
hdss/src/set_persp_transform.py
hdss/src/set_random_noise.py
hdss/src/utils.py
hdss-1.1.2.dist-info/METADATA
hdss-1.1.2.dist-info/WHEEL
hdss-1.1.2.dist-info/RECORD
